TSplotly_Musalar/Ourcode.py
TSplotly_Musalar/__init__.py
tsplotly_musalar-0.0.1.dist-info/METADATA
tsplotly_musalar-0.0.1.dist-info/WHEEL
tsplotly_musalar-0.0.1.dist-info/licenses/LICENCE
tsplotly_musalar-0.0.1.dist-info/RECORD
