Metadata-Version: 2.3
Name: TSplotly_Musalar
Version: 0.0.1
Summary: Taylor series expansion using plotly library
Project-URL: Homepage, https://github.com/Musalar7/2024Oss-Team-Project---Teylor-series
Project-URL: Issues, https://github.com/Musalar7/2024Oss-Team-Project---Teylor-series/issues
Author-email: Group 11 <pjs14344@hanyang.ac.kr>
Classifier: License :: OSI Approved :: MIT License
Classifier: Operating System :: OS Independent
Classifier: Programming Language :: Python :: 3
Requires-Python: >=3.8
